at42qt2120.py
circuitpython_at42qt2120-1.1.1.dist-info/licenses/LICENSE
circuitpython_at42qt2120-1.1.1.dist-info/METADATA
circuitpython_at42qt2120-1.1.1.dist-info/WHEEL
circuitpython_at42qt2120-1.1.1.dist-info/top_level.txt
circuitpython_at42qt2120-1.1.1.dist-info/RECORD
