Metadata-Version: 2.4
Name: circuitpython-at42qt2120
Version: 1.1.1
Summary: A CircuitPython module for the AT42QT2120 capacitive touch sensor IC, (mostly) compatible with Adafruit's MPR121 library.
Author-email: Mike Coats <i.am@mikecoats.com>
License: MIT
Project-URL: Homepage, https://github.com/MikeCoats/CircuitPython_AT42QT2120
Keywords: adafruit,blinka,circuitpython,micropython,capacitive,touch,at42qt2120
Classifier: Intended Audience :: Developers
Classifier: Topic :: Software Development :: Libraries
Classifier: Topic :: Software Development :: Embedded Systems
Classifier: Topic :: System :: Hardware
Classifier: License :: OSI Approved :: MIT License
Classifier: Programming Language :: Python :: 3
License-File: LICENSE
Requires-Dist: Adafruit-Blinka
Requires-Dist: adafruit-circuitpython-busdevice
Provides-Extra: optional
Requires-Dist: pytest; extra == "optional"
Requires-Dist: mkdocs; extra == "optional"
Requires-Dist: mkdocstrings[python]; extra == "optional"
Dynamic: license-file
